LICENSE
MANIFEST.in
README.md
requirements.txt
setup.cfg
setup.py
og_utils.egg-info/PKG-INFO
og_utils.egg-info/SOURCES.txt
og_utils.egg-info/dependency_links.txt
og_utils.egg-info/not-zip-safe
og_utils.egg-info/top_level.txt
ogutils/__init__.py
ogutils/checks.py
ogutils/collections/__init__.py
ogutils/collections/checks.py
ogutils/collections/operators.py
ogutils/collections/transformations.py
ogutils/functions/__init__.py
ogutils/functions/operators.py
ogutils/loggers/__init__.py
ogutils/loggers/default.py
ogutils/loggers/flask.py
ogutils/system/__init__.py
ogutils/system/chdir.py
ogutils/system/streams.py
ogutils/text/__init__.py
ogutils/text/regex.py
ogutils/web/__init__.py
ogutils/web/operators.py