Metadata-Version: 1.1
Name: og-utils
Version: 0.0.5
Summary: A batch of python utilities shared by python repositories at OpenGov
Home-page: https://github.com/OpenGov/og-python-utils
Author: Matthew Seal
Author-email: mseal@opengov.com
License: MIT
Download-URL: https://github.com/OpenGov/og-python-utils/tarball/v0.0.5
Platform: UNKNOWN
Classifier: Development Status :: 4 - Beta
Classifier: Topic :: Utilities
Classifier: License :: OSI Approved :: MIT License
Classifier: Natural Language :: English
Classifier: Programming Language :: Python :: 2 :: Only
